ancast/__init__.py
ancast/__main__.py
ancast/closure.py
ancast/document.py
ancast/evaluate.py
ancast/io_utils.py
ancast/matches.py
ancast/metric.py
ancast/node.py
ancast/ops.py
ancast/params.py
ancast/resource_utils.py
ancast/sentence.py
ancast/word.py
ancast/resources/__init__.py
ancast/resources/abstract_vocab.json
ancast/resources/reification_relations.json
ancast-0.1.1.dist-info/licenses/LICENSE
ancast-0.1.1.dist-info/METADATA
ancast-0.1.1.dist-info/WHEEL
ancast-0.1.1.dist-info/entry_points.txt
ancast-0.1.1.dist-info/top_level.txt
ancast-0.1.1.dist-info/RECORD
