Metadata-Version: 2.4
Name: ancast
Version: 0.1.1
Summary: AnCast++ metric for evaluating UMR semantic graphs
Home-page: https://github.com/umr4nlp/ancast
Author-email: Haibo Sun <hsun@brandeis.edu>, Jayeol Chun <jchun@brandeis.edu>
Project-URL: homepage, https://github.com/umr4nlp/ancast
Classifier: Programming Language :: Python :: 3
Classifier: Programming Language :: Python :: 3.7
Classifier: Programming Language :: Python :: 3.8
Classifier: Programming Language :: Python :: 3.9
Classifier: Programming Language :: Python :: 3.10
Classifier: Programming Language :: Python :: 3.11
Classifier: Programming Language :: Python :: 3.12
Classifier: License :: OSI Approved :: MIT License
Classifier: Operating System :: OS Independent
Requires-Python: >=3.7
License-File: LICENSE
Requires-Dist: numpy
Dynamic: home-page
Dynamic: license-file
